{
  "filters": {
    "byExpr": [
      {
        "type": "Advanced",
        "expression": {
          "Aggregation": {
            "Expression": {
              "Column": {
                "Expression": {
                  "SourceRef": {
                    "Entity": "Online Sales"
                  }
                },
                "Property": "Spending"
              }
            },
            "Function": 1
          }
        },
        "howCreated": 1
      },
      {
        "type": "Advanced",
        "expression": {
          "Measure": {
            "Expression": {
              "SourceRef": {
                "Entity": "Online Sales"
              }
            },
            "Property": "Visits"
          }
        },
        "howCreated": 0
      },
      {
        "type": "Advanced",
        "expression": {
          "HierarchyLevel": {
            "Expression": {
              "Hierarchy": {
                "Expression": {
                  "PropertyVariationSource": {
                    "Expression": {
                      "SourceRef": {
                        "Entity": "Online Sales"
                      }
                    },
                    "Name": "Variation",
                    "Property": "Purchasing Date"
                  }
                },
                "Hierarchy": "Date Hierarchy"
              }
            },
            "Level": "Year"
          }
        },
        "howCreated": 0
      },
      {
        "type": "Categorical",
        "expression": {
          "HierarchyLevel": {
            "Expression": {
              "Hierarchy": {
                "Expression": {
                  "PropertyVariationSource": {
                    "Expression": {
                      "SourceRef": {
                        "Entity": "Online Sales"
                      }
                    },
                    "Name": "Variation",
                    "Property": "Purchasing Date"
                  }
                },
                "Hierarchy": "Date Hierarchy"
              }
            },
            "Level": "Quarter"
          }
        },
        "howCreated": 0
      },
      {
        "type": "Categorical",
        "expression": {
          "HierarchyLevel": {
            "Expression": {
              "Hierarchy": {
                "Expression": {
                  "PropertyVariationSource": {
                    "Expression": {
                      "SourceRef": {
                        "Entity": "Online Sales"
                      }
                    },
                    "Name": "Variation",
                    "Property": "Purchasing Date"
                  }
                },
                "Hierarchy": "Date Hierarchy"
              }
            },
            "Level": "Month"
          }
        },
        "howCreated": 0
      },
      {
        "type": "Advanced",
        "expression": {
          "Measure": {
            "Expression": {
              "SourceRef": {
                "Entity": "Online Sales"
              }
            },
            "Property": "Revenue"
          }
        },
        "howCreated": 0
      }
    ]
  },
  "singleVisual": {
    "visualType": "lineChart",
    "objects": {},
    "activeProjections": {
      "Category": [
        {
          "HierarchyLevel": {
            "Expression": {
              "Hierarchy": {
                "Expression": {
                  "PropertyVariationSource": {
                    "Expression": {
                      "SourceRef": {
                        "Entity": "Online Sales"
                      }
                    },
                    "Name": "Variation",
                    "Property": "Purchasing Date"
                  }
                },
                "Hierarchy": "Date Hierarchy"
              }
            },
            "Level": "Year"
          }
        },
        {
          "HierarchyLevel": {
            "Expression": {
              "Hierarchy": {
                "Expression": {
                  "PropertyVariationSource": {
                    "Expression": {
                      "SourceRef": {
                        "Entity": "Online Sales"
                      }
                    },
                    "Name": "Variation",
                    "Property": "Purchasing Date"
                  }
                },
                "Hierarchy": "Date Hierarchy"
              }
            },
            "Level": "Quarter"
          }
        },
        {
          "HierarchyLevel": {
            "Expression": {
              "Hierarchy": {
                "Expression": {
                  "PropertyVariationSource": {
                    "Expression": {
                      "SourceRef": {
                        "Entity": "Online Sales"
                      }
                    },
                    "Name": "Variation",
                    "Property": "Purchasing Date"
                  }
                },
                "Hierarchy": "Date Hierarchy"
              }
            },
            "Level": "Month"
          }
        }
      ]
    }
  }
}