{
  "displayName": "Pagina 2 Pop Up 1",
  "name": "Bookmark75a7e4fab2b9460877c7",
  "explorationState": {
    "version": "1.3",
    "activeSection": "ReportSection998e2850a99cabad87e8",
    "filters": {
      "byExpr": [
        {
          "name": "Filter",
          "type": "Categorical",
          "filter": {
            "Version": 2,
            "From": [
              {
                "Name": "d",
                "Entity": "Calendar"
              }
            ],
            "Where": [
              {
                "Condition": {
                  "In": {
                    "Expressions": [
                      {
                        "Column": {
                          "Expression": {
                            "SourceRef": {
                              "Source": "d"
                            }
                          },
                          "Property": "Month"
                        }
                      }
                    ],
                    "Values": [
                      [
                        {
                          "Literal": {
                            "Value": "'Jun'"
                          }
                        }
                      ]
                    ]
                  }
                }
              }
            ]
          },
          "expression": {
            "Column": {
              "Expression": {
                "SourceRef": {
                  "Entity": "Calendar"
                }
              },
              "Property": "Month"
            }
          },
          "howCreated": 1
        }
      ]
    },
    "objects": {
      "merge": {
        "outspacePane": [
          {
            "properties": {
              "expanded": {
                "expr": {
                  "Literal": {
                    "Value": "false"
                  }
                }
              }
            }
          }
        ]
      }
    }
  },
  "options": {
    "targetVisualNames": [
      "7a294bf0290b2a762a23",
      "5d14ac0228ea10a55556",
      "ec68108562a62504cb6b"
    ],
    "suppressData": true,
    "suppressActiveSection": true,
    "applyOnlyToTargetVisuals": true
  }
}